cjwmodule/__init__.py
cjwmodule/arrow/__init__.py
cjwmodule/arrow/condition.py
cjwmodule/arrow/dictionary.py
cjwmodule/arrow/format.py
cjwmodule/arrow/testing.py
cjwmodule/arrow/types.py
cjwmodule/http/__init__.py
cjwmodule/http/client.py
cjwmodule/http/errors.py
cjwmodule/http/httpfile.py
cjwmodule/i18n/__init__.py
cjwmodule/i18n/_deprecated_i18n_messages.py
cjwmodule/i18n/el.po
cjwmodule/i18n/en.po
cjwmodule/i18n/funcs.py
cjwmodule/i18n/messages.pot
cjwmodule/i18n/types.py
cjwmodule/spec/README.md
cjwmodule/spec/__init__.py
cjwmodule/spec/loader.py
cjwmodule/spec/paramfield.py
cjwmodule/spec/paramschema.py
cjwmodule/spec/paramschemaparser.py
cjwmodule/spec/schema.yaml
cjwmodule/spec/testing.py
cjwmodule/spec/types.py
cjwmodule/testing/__init__.py
cjwmodule/testing/i18n.py
cjwmodule/types.py
cjwmodule/util/__init__.py
cjwmodule/util/colnames.py
cjwmodule-4.1.12.dist-info/entry_points.txt
cjwmodule-4.1.12.dist-info/WHEEL
cjwmodule-4.1.12.dist-info/METADATA
cjwmodule-4.1.12.dist-info/RECORD
