Metadata-Version: 2.1
Name: cjwmodule
Version: 4.1.12
Summary: Utilities for Workbench modules
License: MIT
Author: Adam Hooper
Author-email: adam@adamhooper.com
Requires-Python: >=3.8.0,<3.9.0
Classifier: License :: OSI Approved :: MIT License
Classifier: Programming Language :: Python :: 3
Classifier: Programming Language :: Python :: 3.8
Requires-Dist: google-re2 (>=0.1.20210401,<0.2.0)
Requires-Dist: httpx (>=0.17,<1.0)
Requires-Dist: jsonschema (>=3.2.0,<3.3.0)
Requires-Dist: pyarrow (>=2.0.0,<5.0.0)
Requires-Dist: pytz (>=2021.1,<2022.0)
Requires-Dist: pyyaml (>=5.4.1,<5.5.0)
Requires-Dist: rfc3987 (>=1.3.8,<1.4.0)
